pdf2tables/__init__.py
pdf2tables/aliyun_tables.py
pdf2tables/image_tables.py
pdf2tables/pdf_tables.py
pdf2tables-0.3.5.dist-info/LICENSE
pdf2tables-0.3.5.dist-info/METADATA
pdf2tables-0.3.5.dist-info/WHEEL
pdf2tables-0.3.5.dist-info/top_level.txt
pdf2tables-0.3.5.dist-info/RECORD
