Metadata-Version: 2.1
Name: pdf2tables
Version: 0.3.5
Summary: extract tables from pdf using camelot, if page is image-base, use ocr to extract
Home-page: https://github.com/chen1tian/pdf2tables
Author: yitian.chen
Author-email: 48295852@qq.com
License: BSD 2-Clause License
Platform: UNKNOWN
Requires-Dist: opencv-python (>=4.0.0.21)
Requires-Dist: pytesseract (>=0.2.6)
Requires-Dist: camelot-py (>=0.7.3)
Requires-Dist: numpy (>=1.16.0)
